riverborn/__init__.py
riverborn/_version.py
riverborn/animals.py
riverborn/blending.py
riverborn/camera.py
riverborn/demo_shadow.py
riverborn/heightfield.py
riverborn/mgl_terrain.py
riverborn/picking.py
riverborn/plants.py
riverborn/ripples.py
riverborn/scene.py
riverborn/screenshot.py
riverborn/shader.py
riverborn/shadow.py
riverborn/shadow_debug.py
riverborn/shadow_debug_demo.py
riverborn/terrain.py
riverborn/tools.py
riverborn/data/animals.json
riverborn/data/terrain.npy
riverborn/models/boat.mtl
riverborn/models/boat.obj
riverborn/models/canoe.glb
riverborn/models/crocodile.mtl
riverborn/models/crocodile.obj
riverborn/models/diffuse.tga
riverborn/models/fern.obj
riverborn/models/flamingo.mtl
riverborn/models/flamingo.obj
riverborn/models/hippo_diffuse.png
riverborn/models/hippopotamus.mtl
riverborn/models/hippopotamus.obj
riverborn/models/oar.obj
riverborn/models/plant01_t.obj
riverborn/models/plant02_t.obj
riverborn/models/plant03_t.obj
riverborn/models/plant04_t.obj
riverborn/models/plant05_t.obj
riverborn/models/plant06_t.obj
riverborn/models/plant07_t.obj
riverborn/models/plant08_t.obj
riverborn/models/plant09_t.obj
riverborn/models/plant10_t.obj
riverborn/models/plant11_t.obj
riverborn/models/plant12_t.obj
riverborn/models/plant13.obj
riverborn/models/plant15.obj
riverborn/models/plant16.obj
riverborn/models/textured.mtl
riverborn/shaders/copy.frag
riverborn/shaders/copy.vert
riverborn/shaders/debug_depth.frag
riverborn/shaders/debug_depth.vert
riverborn/shaders/depth.frag
riverborn/shaders/depth.vert
riverborn/shaders/diffuse.frag
riverborn/shaders/diffuse.vert
riverborn/shaders/ripple.vert
riverborn/shaders/ripple_disturb.frag
riverborn/shaders/ripple_render.frag
riverborn/shaders/ripple_sim.frag
riverborn/shaders/shadow.frag
riverborn/shaders/shadow.vert
riverborn/shaders/shadow_common.glsl
riverborn/shaders/texture_alpha.frag
riverborn/shaders/texture_alpha.vert
riverborn/shaders/water.frag
riverborn/shaders/water.vert
riverborn/sounds/1min.wav
riverborn-1.0.0.dist-info/entry_points.txt
riverborn-1.0.0.dist-info/WHEEL
riverborn-1.0.0.dist-info/METADATA
riverborn-1.0.0.dist-info/RECORD
