Metadata-Version: 2.4
Name: riverborn
Version: 1.0.0
Summary: A river canoeing game for PyWeek 39
Author-email: Daniel Pope <mauve@mauveweb.co.uk>
Requires-Python: >=3.10
Requires-Dist: imageio>=2.37.0
Requires-Dist: moderngl>=5.12.0
Requires-Dist: moderngl-window[glfw, pywavefront]>=3.1.1
Requires-Dist: noise>=1.2.2
Requires-Dist: numpy>=2.2.4
Requires-Dist: wasabi-geom>=2.3.0
Requires-Dist: wasabi2d
Project-URL: Homepage, https://pyweek.org/e/wasabi39/
Project-URL: Repository, https://github.com/lordmauve/riverborn/
